README.md
setup.py
wcscmd
wcs/__init__.py
wcs/commons/__init__.py
wcs/commons/auth.py
wcs/commons/compat.py
wcs/commons/config.py
wcs/commons/crc64_files.py
wcs/commons/error_deal.py
wcs/commons/etag_files.py
wcs/commons/http.py
wcs/commons/logme.py
wcs/commons/putpolicy.py
wcs/commons/util.py
wcs/services/__init__.py
wcs/services/client.py
wcs/services/filemanager.py
wcs/services/fmgr.py
wcs/services/mgrbase.py
wcs/services/multipartupload.py
wcs/services/persistentfop.py
wcs/services/simpleupload.py
wcs/services/streamupload.py
wcs/services/uploadprogressrecorder.py
wcs/services/wslive.py
wcs_python_sdk.egg-info/PKG-INFO
wcs_python_sdk.egg-info/SOURCES.txt
wcs_python_sdk.egg-info/dependency_links.txt
wcs_python_sdk.egg-info/entry_points.txt
wcs_python_sdk.egg-info/requires.txt
wcs_python_sdk.egg-info/top_level.txt